pyhatch/__init__.py
pyhatch/_version.py
pyhatch/fill_template.py
pyhatch/hatch_gui.py
pyhatch/hatch_supt.py
pyhatch/license_templates.py
pyhatch/pypi_version.py
pyhatch/doc_templates/Makefile
pyhatch/doc_templates/authors.rst
pyhatch/doc_templates/build_all_html.py
pyhatch/doc_templates/conf.py
pyhatch/doc_templates/copyright.rst
pyhatch/doc_templates/fulltoc.py
pyhatch/doc_templates/functions.rst
pyhatch/doc_templates/generic_logo.svg
pyhatch/doc_templates/history.rst
pyhatch/doc_templates/index.rst
pyhatch/doc_templates/keyboard_hit.py
pyhatch/doc_templates/make.bat
pyhatch/doc_templates/quickstart.rst
pyhatch/doc_templates/spell_check.bat
pyhatch/doc_templates/spelling_correct_wordlist.txt
pyhatch/doc_templates/sphinxy.py
pyhatch/examples/example_1.py
pyhatch/templates/.pypirc
pyhatch/templates/.travis.yml
pyhatch/templates/AUTHORS.rst
pyhatch/templates/Class_Te_st_File.py
pyhatch/templates/Function_Te_st_File.py
pyhatch/templates/HISTORY.rst
pyhatch/templates/MANIFEST.in
pyhatch/templates/Module_Class.py
pyhatch/templates/Module_Function.py
pyhatch/templates/README.rst
pyhatch/templates/UPLOAD_TO_PyPI.BAT
pyhatch/templates/__init__.py
pyhatch/templates/__init__.pyc
pyhatch/templates/_version.py
pyhatch/templates/example_1.py
pyhatch/templates/history_from_github_api.py
pyhatch/templates/history_from_github_api.py.bak
pyhatch/templates/metadata_reset.py
pyhatch/templates/requirements.txt
pyhatch/templates/setup.cfg
pyhatch/templates/setup.py
pyhatch/templates/tox_linux.ini
pyhatch/templates/tox_windows.ini
pyhatch/tests/__init__.py
pyhatch/tests/test_hatch_supt.py
pyhatch/tests/test_templating.py
PyHatch-0.0.19.dist-info/AUTHORS.rst
PyHatch-0.0.19.dist-info/LICENSE.txt
PyHatch-0.0.19.dist-info/METADATA
PyHatch-0.0.19.dist-info/WHEEL
PyHatch-0.0.19.dist-info/entry_points.txt
PyHatch-0.0.19.dist-info/top_level.txt
PyHatch-0.0.19.dist-info/RECORD
