Metadata-Version: 2.1
Name: PyHatch
Version: 0.0.19
Summary: PyHatch initializes files and directory structure for new python projects.
Home-page: http://pyhatch.readthedocs.org/en/latest/
Author: Charlie Taylor
Author-email: cet@appliedpython.com
License: GPL-3
Download-URL: https://github.com/sonofeft/PyHatch
Keywords: pyhatch setuptools development
Platform: any
Classifier: Development Status :: 4 - Beta
Classifier: Operating System :: OS Independent
Classifier: Intended Audience :: Developers
Classifier: Intended Audience :: End Users/Desktop
Classifier: Topic :: Software Development :: Build Tools
Classifier: License :: OSI Approved :: GNU General Public License v3 (GPLv3)
Classifier: Programming Language :: Python :: 2
Classifier: Programming Language :: Python :: 2.7
Classifier: Programming Language :: Python :: 3
Classifier: Programming Language :: Python :: 3.7
Requires-Dist: future
Provides-Extra: dev
Requires-Dist: check-manifest ; extra == 'dev'
Provides-Extra: test
Requires-Dist: coverage ; extra == 'test'
